ride/__init__.py
ride/automl_processor.py
ride/cli.py
ride/utils.py
ride_cli-0.3.3.dist-info/licenses/LICENSE
ride_cli-0.3.3.dist-info/METADATA
ride_cli-0.3.3.dist-info/WHEEL
ride_cli-0.3.3.dist-info/entry_points.txt
ride_cli-0.3.3.dist-info/top_level.txt
ride_cli-0.3.3.dist-info/RECORD
