Metadata-Version: 2.4
Name: ride-cli
Version: 0.3.3
Summary: RIDE: Rapid Insights Data Engine - An open-source toolkit for data analysis in terminal
Home-page: https://github.com/sudhanshumukherjeexx/ride-cli
Author: Sudhanshu Mukherjee
Author-email: Sudhanshu Mukherjee <sudhanshumukherjeexx@gmail.com>
License: MIT
Project-URL: Homepage, https://github.com/sudhanshumukherjeexx/ride-cli
Project-URL: Documentation, https://github.com/sudhanshumukherjeexx/ride-cli#readme
Project-URL: Repository, https://github.com/sudhanshumukherjeexx/ride-cli.git
Project-URL: Issues, https://github.com/sudhanshumukherjeexx/ride-cli/issues
Project-URL: Changelog, https://github.com/sudhanshumukherjeexx/ride-cli/blob/main/CHANGELOG.md
Keywords: data-preprocessing,machine-learning,data-science,cli,data-exploration
Classifier: Development Status :: 4 - Beta
Classifier: Intended Audience :: Developers
Classifier: Intended Audience :: Science/Research
Classifier: License :: OSI Approved :: MIT License
Classifier: Operating System :: OS Independent
Classifier: Programming Language :: Python :: 3.10
Classifier: Programming Language :: Python :: 3.11
Classifier: Programming Language :: Python :: 3.12
Classifier: Topic :: Scientific/Engineering :: Information Analysis
Classifier: Topic :: Software Development :: Libraries :: Python Modules
Requires-Python: >=3.10
License-File: LICENSE
Requires-Dist: blessed==1.19.1
Requires-Dist: imbalanced_learn==0.10.1
Requires-Dist: imblearn==0.0
Requires-Dist: joblib==1.2.0
Requires-Dist: matplotlib==3.10.1
Requires-Dist: numpy==2.2.3
Requires-Dist: pandas==2.2.3
Requires-Dist: plotext==5.2.8
Requires-Dist: pydantic==2.10.6
Requires-Dist: pyfiglet==0.8.post1
Requires-Dist: pytest==7.3.1
Requires-Dist: scikit_learn==1.6.1
Requires-Dist: scipy==1.15.2
Requires-Dist: termcolor==2.3.0
Requires-Dist: pyarrow==19.0.1
Requires-Dist: seaborn==0.11.2
Requires-Dist: tqdm==4.66.1
Requires-Dist: lightgbm==4.6.0
Requires-Dist: xgboost==2.1.4
Requires-Dist: nbformat==5.10.0
Requires-Dist: setuptools==76.1.0
Requires-Dist: openpyxl>=3.0.0
Provides-Extra: dev
Requires-Dist: pytest; extra == "dev"
Requires-Dist: twine; extra == "dev"
Requires-Dist: wheel; extra == "dev"
Requires-Dist: black; extra == "dev"
Requires-Dist: isort; extra == "dev"
Requires-Dist: flake8; extra == "dev"
Dynamic: author
Dynamic: home-page
Dynamic: license-file
Dynamic: requires-python
